nicehash/__init__.py
nicehash/client.py
myb_nicehash_api-2.3.0.dist-info/LICENSE
myb_nicehash_api-2.3.0.dist-info/METADATA
myb_nicehash_api-2.3.0.dist-info/WHEEL
myb_nicehash_api-2.3.0.dist-info/top_level.txt
myb_nicehash_api-2.3.0.dist-info/RECORD
