Metadata-Version: 2.1
Name: myb-nicehash-api
Version: 2.3.0
Summary: Python library for communicating with the NiceHash API
Home-page: https://github.com/mine-your-business/myb-nicehash-api
Author: Mine Your Business
Author-email: mine.your.business.crypto@gmail.com
License: GPL-3
Classifier: Programming Language :: Python :: 3
Classifier: License :: OSI Approved :: GNU General Public License v3 (GPLv3)
Classifier: Operating System :: OS Independent
Requires-Python: >=3.7
License-File: LICENSE
Requires-Dist: requests (>=2.25.1)
